{
"event_ID": "00017106",
"person_Id": "0074",
"source_text": "在我进占盘县后，敌人便一窝蜂似的向东扑来。而我军却掉头向西，进入云南，经宣威、沾益、马龙、寻甸到了普渡河。在普渡河，遭到云南军阀龙云率全部滇军的堵击，展开了激烈的战斗。这时，贺总又指挥部队连夜行军，直逼昆明。敌人吓得惊慌失措，生怕我军进攻昆明，端了他们的老窝，慌忙把滇军主力调回昆明。而我军采用“虚晃一枪，回马便走”的战术，转而向西攻占富民，把滇军主力扔在屁股后面了。我军又继续向西挺进，敌人害怕我军进攻下关、大理，又连忙调兵去防守。蒋介石也把他的中央大军调来增援，并亲自坐上飞机在空中督战。龙云也派飞机侦察、轰炸，妄想在金沙江、澜沧江之间把红二、六军团一口吞掉。贺总用“调虎离山”、“避实就虚”的战法，牵着敌人的鼻子团团乱转，使敌十几万大军疲于奔命，而我军在滇中却如入无人之境。",
"type": "",
"ei": "转",
"pc": "贺龙",
"tm": "",
"loc": "",
"em": "贺龙率部牵着敌人团团转",
"timID": "017"
}