{
 "eventId": "00008208",
 "personId": "0034",
 "sourceText": "习仲勋被彭德怀的精神感动了，他采纳了彭德怀的意见，专门召开了一次团以上干部会。彭德怀在会上坦诚地说：“这些日子，部队过沙漠确实很艰苦，累、热不说，主要是缺水，有的部队甚至渴死了人，可是在这种时候，我彭德怀居然吃上了黄瓜。在这里，我首先向大家作一个深刻的自我检讨，我彭德怀犯了严重的官僚主义错误！”彭德怀说到这里，摘下军帽，郑重其事地向众人深鞠了一躬。习仲勋见状，插话道：“其实，这些黄瓜彭总并没有吃，全让他送给伤病员了。”彭德怀打断习仲勋：“你们也许觉得，不就是一根黄瓜吗？我彭德怀堂堂一个兵团司令，吃了也就吃了，何必小题大做呢？但是我要告诉你们，我今天就是要小题大做！因为什么？因为我们的军队和国民党军队最大的区别就是官兵平等。今天我这个兵团司令吃了一根黄瓜，明天你们这些纵队司令就会心安理得地跟我学，去吃一只鸡，再过几天，旅长、团长、营长、连长也会上行下效，官兵之间的距离就是这样一点点拉开的！”彭德怀说到这儿，又把脸转向习仲勋，严肃地说：“习政委，我本人的检讨今晚就会交给党支部，对其他相关人员的处分，由你这个支部书记作出决定。”",
 "ei": "说",
 "pc": "彭德怀",
 "tm": "",
 "loc": "",
 "em": "彭德怀自我检讨，不该在缺水时候吃黄瓜，官兵应该平等"
}